{"071.jpg90071": {"filename": "071.jpg", "size": 90071, "regions": [{"shape_attributes": {"name": "rect", "x": 434, "y": 307, "width": 33, "height": 37}, "region_attributes": {}}, {"shape_attributes": {"name": "rect", "x": 807, "y": 139, "width": 36, "height": 38}, "region_attributes": {}}, {"shape_attributes": {"name": "rect", "x": 906, "y": 131, "width": 35, "height": 34}, "region_attributes": {}}, {"shape_attributes": {"name": "rect", "x": 1046, "y": 107, "width": 37, "height": 44}, "region_attributes": {}}, {"shape_attributes": {"name": "rect", "x": 1371, "y": 195, "width": 47, "height": 44}, "region_attributes": {}}, {"shape_attributes": {"name": "rect", "x": 1510, "y": 253, "width": 34, "height": 38}, "region_attributes": {}}, {"shape_attributes": {"name": "rect", "x": 1430, "y": 296, "width": 35, "height": 39}, "region_attributes": {}}, {"shape_attributes": {"name": "rect", "x": 1423, "y": 358, "width": 32, "height": 37}, "region_attributes": {}}, {"shape_attributes": {"name": "rect", "x": 1366, "y": 458, "width": 34, "height": 43}, "region_attributes": {}}, {"shape_attributes": {"name": "rect", "x": 1467, "y": 538, "width": 46, "height": 38}, "region_attributes": {}}, {"shape_attributes": {"name": "rect", "x": 1782, "y": 559, "width": 40, "height": 50}, "region_attributes": {}}, {"shape_attributes": {"name": "rect", "x": 1802, "y": 665, "width": 44, "height": 47}, "region_attributes": {}}, {"shape_attributes": {"name": "rect", "x": 577, "y": 934, "width": 51, "height": 53}, "region_attributes": {}}, {"shape_attributes": {"name": "rect", "x": 590, "y": 762, "width": 42, "height": 41}, "region_attributes": {}}, {"shape_attributes": {"name": "rect", "x": 626, "y": 806, "width": 45, "height": 47}, "region_attributes": {}}, {"shape_attributes": {"name": "rect", "x": 881, "y": 907, "width": 34, "height": 39}, "region_attributes": {}}, {"shape_attributes": {"name": "rect", "x": 828, "y": 1024, "width": 42, "height": 43}, "region_attributes": {}}, {"shape_attributes": {"name": "rect", "x": 67, "y": 875, "width": 49, "height": 47}, "region_attributes": {}}], "file_attributes": {}}}