{"128.jpg51439": {"filename": "128.jpg", "size": 51439, "regions": [{"shape_attributes": {"name": "rect", "x": 786, "y": 814, "width": 45, "height": 57}, "region_attributes": {}}, {"shape_attributes": {"name": "rect", "x": 779, "y": 282, "width": 33, "height": 41}, "region_attributes": {}}, {"shape_attributes": {"name": "rect", "x": 1464, "y": 861, "width": 46, "height": 55}, "region_attributes": {}}, {"shape_attributes": {"name": "rect", "x": 1429, "y": 960, "width": 49, "height": 64}, "region_attributes": {}}, {"shape_attributes": {"name": "rect", "x": 1313, "y": 891, "width": 57, "height": 62}, "region_attributes": {}}, {"shape_attributes": {"name": "rect", "x": 886, "y": 928, "width": 49, "height": 65}, "region_attributes": {}}, {"shape_attributes": {"name": "rect", "x": 1315, "y": 294, "width": 34, "height": 42}, "region_attributes": {}}, {"shape_attributes": {"name": "rect", "x": 1296, "y": 265, "width": 33, "height": 41}, "region_attributes": {}}, {"shape_attributes": {"name": "rect", "x": 319, "y": 399, "width": 34, "height": 46}, "region_attributes": {}}, {"shape_attributes": {"name": "rect", "x": 1142, "y": 169, "width": 22, "height": 31}, "region_attributes": {}}, {"shape_attributes": {"name": "rect", "x": 1099, "y": 171, "width": 21, "height": 28}, "region_attributes": {}}, {"shape_attributes": {"name": "rect", "x": 55, "y": 695, "width": 42, "height": 52}, "region_attributes": {}}, {"shape_attributes": {"name": "rect", "x": 386, "y": 928, "width": 51, "height": 63}, "region_attributes": {}}, {"shape_attributes": {"name": "rect", "x": 236, "y": 199, "width": 28, "height": 33}, "region_attributes": {}}, {"shape_attributes": {"name": "rect", "x": 1098, "y": 136, "width": 26, "height": 31}, "region_attributes": {}}, {"shape_attributes": {"name": "rect", "x": 226, "y": 174, "width": 30, "height": 34}, "region_attributes": {}}, {"shape_attributes": {"name": "rect", "x": 0, "y": 309, "width": 26, "height": 40}, "region_attributes": {}}, {"shape_attributes": {"name": "rect", "x": 1566, "y": 1021, "width": 53, "height": 58}, "region_attributes": {}}, {"shape_attributes": {"name": "rect", "x": 872, "y": 783, "width": 47, "height": 56}, "region_attributes": {}}, {"shape_attributes": {"name": "rect", "x": 752, "y": 910, "width": 53, "height": 59}, "region_attributes": {}}, {"shape_attributes": {"name": "rect", "x": 21, "y": 14, "width": 20, "height": 28}, "region_attributes": {}}, {"shape_attributes": {"name": "rect", "x": 1456, "y": 95, "width": 29, "height": 34}, "region_attributes": {}}, {"shape_attributes": {"name": "rect", "x": 1442, "y": 113, "width": 32, "height": 41}, "region_attributes": {}}, {"shape_attributes": {"name": "rect", "x": 4, "y": 34, "width": 22, "height": 29}, "region_attributes": {}}, {"shape_attributes": {"name": "rect", "x": 18, "y": 72, "width": 23, "height": 31}, "region_attributes": {}}, {"shape_attributes": {"name": "rect", "x": 59, "y": 79, "width": 27, "height": 34}, "region_attributes": {}}, {"shape_attributes": {"name": "rect", "x": 349, "y": 496, "width": 41, "height": 49}, "region_attributes": {}}, {"shape_attributes": {"name": "rect", "x": 14, "y": 750, "width": 43, "height": 43}, "region_attributes": {}}], "file_attributes": {}}}