{"011.jpg56846": {"filename": "011.jpg", "size": 56846, "regions": [{"shape_attributes": {"name": "rect", "x": 998, "y": 537, "width": 40, "height": 58}, "region_attributes": {}}, {"shape_attributes": {"name": "rect", "x": 1601, "y": 424, "width": 47, "height": 57}, "region_attributes": {}}, {"shape_attributes": {"name": "rect", "x": 1517, "y": 111, "width": 34, "height": 39}, "region_attributes": {}}, {"shape_attributes": {"name": "rect", "x": 957, "y": 135, "width": 24, "height": 39}, "region_attributes": {}}, {"shape_attributes": {"name": "rect", "x": 844, "y": 174, "width": 29, "height": 42}, "region_attributes": {}}, {"shape_attributes": {"name": "rect", "x": 893, "y": 577, "width": 37, "height": 50}, "region_attributes": {}}, {"shape_attributes": {"name": "rect", "x": 812, "y": 352, "width": 35, "height": 45}, "region_attributes": {}}, {"shape_attributes": {"name": "rect", "x": 1410, "y": 939, "width": 47, "height": 58}, "region_attributes": {}}, {"shape_attributes": {"name": "rect", "x": 1785, "y": 121, "width": 26, "height": 29}, "region_attributes": {}}, {"shape_attributes": {"name": "rect", "x": 1789, "y": 25, "width": 27, "height": 36}, "region_attributes": {}}, {"shape_attributes": {"name": "rect", "x": 984, "y": 70, "width": 27, "height": 37}, "region_attributes": {}}, {"shape_attributes": {"name": "rect", "x": 313, "y": 504, "width": 36, "height": 47}, "region_attributes": {}}, {"shape_attributes": {"name": "rect", "x": 1293, "y": 872, "width": 59, "height": 69}, "region_attributes": {}}, {"shape_attributes": {"name": "rect", "x": 163, "y": 257, "width": 38, "height": 36}, "region_attributes": {}}, {"shape_attributes": {"name": "rect", "x": 192, "y": 269, "width": 33, "height": 36}, "region_attributes": {}}, {"shape_attributes": {"name": "rect", "x": 994, "y": 203, "width": 31, "height": 39}, "region_attributes": {}}, {"shape_attributes": {"name": "rect", "x": 1226, "y": 258, "width": 33, "height": 43}, "region_attributes": {}}, {"shape_attributes": {"name": "rect", "x": 1383, "y": 51, "width": 25, "height": 34}, "region_attributes": {}}, {"shape_attributes": {"name": "rect", "x": 1052, "y": 148, "width": 30, "height": 38}, "region_attributes": {}}, {"shape_attributes": {"name": "rect", "x": 1260, "y": 216, "width": 29, "height": 39}, "region_attributes": {}}, {"shape_attributes": {"name": "rect", "x": 1437, "y": 862, "width": 43, "height": 57}, "region_attributes": {}}, {"shape_attributes": {"name": "rect", "x": 2, "y": 263, "width": 36, "height": 44}, "region_attributes": {}}, {"shape_attributes": {"name": "rect", "x": 1867, "y": 87, "width": 24, "height": 27}, "region_attributes": {}}, {"shape_attributes": {"name": "rect", "x": 1557, "y": 1010, "width": 53, "height": 59}, "region_attributes": {}}, {"shape_attributes": {"name": "rect", "x": 1706, "y": 59, "width": 29, "height": 32}, "region_attributes": {}}, {"shape_attributes": {"name": "rect", "x": 1706, "y": 79, "width": 39, "height": 39}, "region_attributes": {}}, {"shape_attributes": {"name": "rect", "x": 1285, "y": 327, "width": 35, "height": 37}, "region_attributes": {}}, {"shape_attributes": {"name": "rect", "x": 860, "y": 887, "width": 47, "height": 54}, "region_attributes": {}}, {"shape_attributes": {"name": "rect", "x": 364, "y": 992, "width": 54, "height": 51}, "region_attributes": {}}, {"shape_attributes": {"name": "rect", "x": 32, "y": 671, "width": 46, "height": 44}, "region_attributes": {}}, {"shape_attributes": {"name": "rect", "x": 5, "y": 715, "width": 30, "height": 54}, "region_attributes": {}}], "file_attributes": {}}}