{"079.jpg58175": {"filename": "079.jpg", "size": 58175, "regions": [{"shape_attributes": {"name": "rect", "x": 1106, "y": 623, "width": 39, "height": 45}, "region_attributes": {}}, {"shape_attributes": {"name": "rect", "x": 656, "y": 244, "width": 28, "height": 34}, "region_attributes": {}}, {"shape_attributes": {"name": "rect", "x": 608, "y": 894, "width": 46, "height": 52}, "region_attributes": {}}, {"shape_attributes": {"name": "rect", "x": 978, "y": 782, "width": 44, "height": 56}, "region_attributes": {}}, {"shape_attributes": {"name": "rect", "x": 557, "y": 352, "width": 33, "height": 35}, "region_attributes": {}}, {"shape_attributes": {"name": "rect", "x": 1586, "y": 343, "width": 29, "height": 45}, "region_attributes": {}}, {"shape_attributes": {"name": "rect", "x": 113, "y": 568, "width": 27, "height": 37}, "region_attributes": {}}, {"shape_attributes": {"name": "rect", "x": 1036, "y": 644, "width": 38, "height": 54}, "region_attributes": {}}, {"shape_attributes": {"name": "rect", "x": 920, "y": 53, "width": 19, "height": 28}, "region_attributes": {}}, {"shape_attributes": {"name": "rect", "x": 994, "y": 489, "width": 38, "height": 45}, "region_attributes": {}}, {"shape_attributes": {"name": "rect", "x": 843, "y": 685, "width": 44, "height": 49}, "region_attributes": {}}, {"shape_attributes": {"name": "rect", "x": 776, "y": 510, "width": 37, "height": 46}, "region_attributes": {}}, {"shape_attributes": {"name": "rect", "x": 1133, "y": 27, "width": 22, "height": 34}, "region_attributes": {}}, {"shape_attributes": {"name": "rect", "x": 1039, "y": 117, "width": 24, "height": 37}, "region_attributes": {}}, {"shape_attributes": {"name": "rect", "x": 811, "y": 136, "width": 22, "height": 33}, "region_attributes": {}}, {"shape_attributes": {"name": "rect", "x": 1079, "y": 14, "width": 19, "height": 29}, "region_attributes": {}}, {"shape_attributes": {"name": "rect", "x": 90, "y": 800, "width": 45, "height": 55}, "region_attributes": {}}, {"shape_attributes": {"name": "rect", "x": 1426, "y": 146, "width": 24, "height": 27}, "region_attributes": {}}, {"shape_attributes": {"name": "rect", "x": 1349, "y": 242, "width": 25, "height": 33}, "region_attributes": {}}, {"shape_attributes": {"name": "rect", "x": 846, "y": 126, "width": 22, "height": 35}, "region_attributes": {}}, {"shape_attributes": {"name": "rect", "x": 181, "y": 770, "width": 42, "height": 58}, "region_attributes": {}}, {"shape_attributes": {"name": "rect", "x": 1090, "y": 130, "width": 21, "height": 31}, "region_attributes": {}}, {"shape_attributes": {"name": "rect", "x": 864, "y": 404, "width": 26, "height": 33}, "region_attributes": {}}, {"shape_attributes": {"name": "rect", "x": 944, "y": 125, "width": 19, "height": 29}, "region_attributes": {}}, {"shape_attributes": {"name": "rect", "x": 1815, "y": 73, "width": 25, "height": 27}, "region_attributes": {}}, {"shape_attributes": {"name": "rect", "x": 1026, "y": 2, "width": 25, "height": 34}, "region_attributes": {}}, {"shape_attributes": {"name": "rect", "x": 1260, "y": 201, "width": 24, "height": 35}, "region_attributes": {}}], "file_attributes": {}}}