{"139.jpg60111": {"filename": "139.jpg", "size": 60111, "regions": [{"shape_attributes": {"name": "rect", "x": 1097, "y": 122, "width": 25, "height": 34}, "region_attributes": {}}, {"shape_attributes": {"name": "rect", "x": 660, "y": 214, "width": 28, "height": 31}, "region_attributes": {}}, {"shape_attributes": {"name": "rect", "x": 980, "y": 233, "width": 27, "height": 39}, "region_attributes": {}}, {"shape_attributes": {"name": "rect", "x": 550, "y": 23, "width": 19, "height": 28}, "region_attributes": {}}, {"shape_attributes": {"name": "rect", "x": 1436, "y": 435, "width": 36, "height": 41}, "region_attributes": {}}, {"shape_attributes": {"name": "rect", "x": 147, "y": 634, "width": 32, "height": 45}, "region_attributes": {}}, {"shape_attributes": {"name": "rect", "x": 728, "y": 104, "width": 24, "height": 31}, "region_attributes": {}}, {"shape_attributes": {"name": "rect", "x": 1038, "y": 111, "width": 22, "height": 30}, "region_attributes": {}}, {"shape_attributes": {"name": "rect", "x": 1066, "y": 47, "width": 22, "height": 30}, "region_attributes": {}}, {"shape_attributes": {"name": "rect", "x": 319, "y": 538, "width": 35, "height": 44}, "region_attributes": {}}, {"shape_attributes": {"name": "rect", "x": 850, "y": 159, "width": 21, "height": 31}, "region_attributes": {}}, {"shape_attributes": {"name": "rect", "x": 1072, "y": 314, "width": 30, "height": 46}, "region_attributes": {}}, {"shape_attributes": {"name": "rect", "x": 38, "y": 473, "width": 35, "height": 43}, "region_attributes": {}}, {"shape_attributes": {"name": "rect", "x": 1067, "y": 427, "width": 29, "height": 37}, "region_attributes": {}}, {"shape_attributes": {"name": "rect", "x": 662, "y": 6, "width": 18, "height": 28}, "region_attributes": {}}, {"shape_attributes": {"name": "rect", "x": 991, "y": 96, "width": 20, "height": 32}, "region_attributes": {}}, {"shape_attributes": {"name": "rect", "x": 1041, "y": 246, "width": 20, "height": 31}, "region_attributes": {}}, {"shape_attributes": {"name": "rect", "x": 618, "y": 0, "width": 20, "height": 25}, "region_attributes": {}}, {"shape_attributes": {"name": "rect", "x": 71, "y": 361, "width": 29, "height": 33}, "region_attributes": {}}, {"shape_attributes": {"name": "rect", "x": 1012, "y": 441, "width": 31, "height": 43}, "region_attributes": {}}, {"shape_attributes": {"name": "rect", "x": 387, "y": 511, "width": 38, "height": 48}, "region_attributes": {}}, {"shape_attributes": {"name": "rect", "x": 911, "y": 238, "width": 23, "height": 33}, "region_attributes": {}}, {"shape_attributes": {"name": "rect", "x": 784, "y": 305, "width": 25, "height": 41}, "region_attributes": {}}, {"shape_attributes": {"name": "rect", "x": 900, "y": 317, "width": 27, "height": 35}, "region_attributes": {}}, {"shape_attributes": {"name": "rect", "x": 1014, "y": 50, "width": 16, "height": 23}, "region_attributes": {}}, {"shape_attributes": {"name": "rect", "x": 965, "y": 562, "width": 46, "height": 47}, "region_attributes": {}}, {"shape_attributes": {"name": "rect", "x": 168, "y": 973, "width": 55, "height": 55}, "region_attributes": {}}, {"shape_attributes": {"name": "rect", "x": 1535, "y": 276, "width": 27, "height": 38}, "region_attributes": {}}, {"shape_attributes": {"name": "rect", "x": 763, "y": 0, "width": 19, "height": 16}, "region_attributes": {}}, {"shape_attributes": {"name": "rect", "x": 0, "y": 595, "width": 27, "height": 53}, "region_attributes": {}}, {"shape_attributes": {"name": "rect", "x": 968, "y": 20, "width": 24, "height": 32}, "region_attributes": {}}, {"shape_attributes": {"name": "rect", "x": 896, "y": 44, "width": 19, "height": 29}, "region_attributes": {}}, {"shape_attributes": {"name": "rect", "x": 1645, "y": 466, "width": 39, "height": 47}, "region_attributes": {}}, {"shape_attributes": {"name": "rect", "x": 1812, "y": 94, "width": 27, "height": 27}, "region_attributes": {}}, {"shape_attributes": {"name": "rect", "x": 744, "y": 314, "width": 29, "height": 37}, "region_attributes": {}}, {"shape_attributes": {"name": "rect", "x": 778, "y": 447, "width": 37, "height": 39}, "region_attributes": {}}, {"shape_attributes": {"name": "rect", "x": 589, "y": 0, "width": 19, "height": 13}, "region_attributes": {}}], "file_attributes": {}}}