{"121.jpg38851": {"filename": "121.jpg", "size": 38851, "regions": [{"shape_attributes": {"name": "rect", "x": 538, "y": 245, "width": 20, "height": 22}, "region_attributes": {}}, {"shape_attributes": {"name": "rect", "x": 742, "y": 594, "width": 36, "height": 39}, "region_attributes": {}}, {"shape_attributes": {"name": "rect", "x": 21, "y": 392, "width": 29, "height": 32}, "region_attributes": {}}, {"shape_attributes": {"name": "rect", "x": 1162, "y": 582, "width": 49, "height": 42}, "region_attributes": {}}, {"shape_attributes": {"name": "rect", "x": 412, "y": 134, "width": 16, "height": 20}, "region_attributes": {}}, {"shape_attributes": {"name": "rect", "x": 805, "y": 478, "width": 28, "height": 31}, "region_attributes": {}}, {"shape_attributes": {"name": "rect", "x": 138, "y": 162, "width": 23, "height": 27}, "region_attributes": {}}, {"shape_attributes": {"name": "rect", "x": 99, "y": 164, "width": 21, "height": 22}, "region_attributes": {}}, {"shape_attributes": {"name": "rect", "x": 494, "y": 70, "width": 13, "height": 15}, "region_attributes": {}}, {"shape_attributes": {"name": "rect", "x": 36, "y": 180, "width": 16, "height": 18}, "region_attributes": {}}, {"shape_attributes": {"name": "rect", "x": 1166, "y": 500, "width": 38, "height": 42}, "region_attributes": {}}, {"shape_attributes": {"name": "rect", "x": 1125, "y": 148, "width": 22, "height": 24}, "region_attributes": {}}, {"shape_attributes": {"name": "rect", "x": 922, "y": 380, "width": 22, "height": 24}, "region_attributes": {}}, {"shape_attributes": {"name": "rect", "x": 313, "y": 169, "width": 19, "height": 21}, "region_attributes": {}}, {"shape_attributes": {"name": "rect", "x": 119, "y": 190, "width": 17, "height": 17}, "region_attributes": {}}, {"shape_attributes": {"name": "rect", "x": 257, "y": 391, "width": 22, "height": 25}, "region_attributes": {}}, {"shape_attributes": {"name": "rect", "x": 732, "y": 376, "width": 38, "height": 37}, "region_attributes": {}}, {"shape_attributes": {"name": "rect", "x": 1173, "y": 159, "width": 23, "height": 23}, "region_attributes": {}}], "file_attributes": {}}}