{"102.jpg48278": {"filename": "102.jpg", "size": 48278, "regions": [{"shape_attributes": {"name": "rect", "x": 1764, "y": 636, "width": 46, "height": 52}, "region_attributes": {}}, {"shape_attributes": {"name": "rect", "x": 325, "y": 323, "width": 34, "height": 38}, "region_attributes": {}}, {"shape_attributes": {"name": "rect", "x": 1057, "y": 192, "width": 32, "height": 37}, "region_attributes": {}}, {"shape_attributes": {"name": "rect", "x": 976, "y": 171, "width": 33, "height": 43}, "region_attributes": {}}, {"shape_attributes": {"name": "rect", "x": 554, "y": 363, "width": 35, "height": 50}, "region_attributes": {}}, {"shape_attributes": {"name": "rect", "x": 1265, "y": 911, "width": 53, "height": 75}, "region_attributes": {}}, {"shape_attributes": {"name": "rect", "x": 1134, "y": 184, "width": 38, "height": 58}, "region_attributes": {}}, {"shape_attributes": {"name": "rect", "x": 1817, "y": 644, "width": 39, "height": 34}, "region_attributes": {}}, {"shape_attributes": {"name": "rect", "x": 1403, "y": 889, "width": 55, "height": 65}, "region_attributes": {}}, {"shape_attributes": {"name": "rect", "x": 582, "y": 27, "width": 25, "height": 32}, "region_attributes": {}}, {"shape_attributes": {"name": "rect", "x": 679, "y": 414, "width": 37, "height": 42}, "region_attributes": {}}, {"shape_attributes": {"name": "rect", "x": 804, "y": 108, "width": 22, "height": 33}, "region_attributes": {}}, {"shape_attributes": {"name": "rect", "x": 42, "y": 337, "width": 38, "height": 41}, "region_attributes": {}}, {"shape_attributes": {"name": "rect", "x": 540, "y": 35, "width": 25, "height": 37}, "region_attributes": {}}, {"shape_attributes": {"name": "rect", "x": 1804, "y": 974, "width": 58, "height": 73}, "region_attributes": {}}, {"shape_attributes": {"name": "rect", "x": 773, "y": 10, "width": 34, "height": 38}, "region_attributes": {}}, {"shape_attributes": {"name": "rect", "x": 743, "y": 229, "width": 30, "height": 39}, "region_attributes": {}}, {"shape_attributes": {"name": "rect", "x": 1157, "y": 213, "width": 27, "height": 43}, "region_attributes": {}}, {"shape_attributes": {"name": "rect", "x": 585, "y": 147, "width": 34, "height": 34}, "region_attributes": {}}, {"shape_attributes": {"name": "rect", "x": 651, "y": 211, "width": 32, "height": 32}, "region_attributes": {}}, {"shape_attributes": {"name": "rect", "x": 702, "y": 191, "width": 29, "height": 30}, "region_attributes": {}}, {"shape_attributes": {"name": "rect", "x": 859, "y": 51, "width": 29, "height": 24}, "region_attributes": {}}, {"shape_attributes": {"name": "rect", "x": 864, "y": 89, "width": 37, "height": 37}, "region_attributes": {}}, {"shape_attributes": {"name": "rect", "x": 923, "y": 123, "width": 27, "height": 32}, "region_attributes": {}}, {"shape_attributes": {"name": "rect", "x": 925, "y": 172, "width": 27, "height": 25}, "region_attributes": {}}], "file_attributes": {}}}