{"142.jpg76333": {"filename": "142.jpg", "size": 76333, "regions": [{"shape_attributes": {"name": "rect", "x": 301, "y": 462, "width": 8, "height": 12}, "region_attributes": {}}, {"shape_attributes": {"name": "rect", "x": 319, "y": 462, "width": 12, "height": 6}, "region_attributes": {}}, {"shape_attributes": {"name": "rect", "x": 333, "y": 417, "width": 10, "height": 9}, "region_attributes": {}}, {"shape_attributes": {"name": "rect", "x": 371, "y": 409, "width": 8, "height": 8}, "region_attributes": {}}, {"shape_attributes": {"name": "rect", "x": 422, "y": 423, "width": 7, "height": 9}, "region_attributes": {}}, {"shape_attributes": {"name": "rect", "x": 442, "y": 416, "width": 10, "height": 9}, "region_attributes": {}}, {"shape_attributes": {"name": "rect", "x": 443, "y": 431, "width": 10, "height": 14}, "region_attributes": {}}, {"shape_attributes": {"name": "rect", "x": 467, "y": 424, "width": 10, "height": 11}, "region_attributes": {}}, {"shape_attributes": {"name": "rect", "x": 492, "y": 423, "width": 8, "height": 8}, "region_attributes": {}}, {"shape_attributes": {"name": "rect", "x": 508, "y": 429, "width": 9, "height": 9}, "region_attributes": {}}], "file_attributes": {}}}