{"149.jpg29763": {"filename": "149.jpg", "size": 29763, "regions": [{"shape_attributes": {"name": "rect", "x": 209, "y": 616, "width": 58, "height": 60}, "region_attributes": {}}, {"shape_attributes": {"name": "rect", "x": 333, "y": 605, "width": 57, "height": 56}, "region_attributes": {}}, {"shape_attributes": {"name": "rect", "x": 447, "y": 445, "width": 51, "height": 49}, "region_attributes": {}}, {"shape_attributes": {"name": "rect", "x": 473, "y": 27, "width": 38, "height": 34}, "region_attributes": {}}, {"shape_attributes": {"name": "rect", "x": 573, "y": 58, "width": 40, "height": 46}, "region_attributes": {}}, {"shape_attributes": {"name": "rect", "x": 795, "y": 1, "width": 29, "height": 16}, "region_attributes": {}}, {"shape_attributes": {"name": "rect", "x": 802, "y": 88, "width": 43, "height": 33}, "region_attributes": {}}, {"shape_attributes": {"name": "rect", "x": 808, "y": 151, "width": 34, "height": 39}, "region_attributes": {}}, {"shape_attributes": {"name": "rect", "x": 812, "y": 217, "width": 35, "height": 30}, "region_attributes": {}}, {"shape_attributes": {"name": "rect", "x": 718, "y": 324, "width": 44, "height": 43}, "region_attributes": {}}, {"shape_attributes": {"name": "rect", "x": 799, "y": 314, "width": 41, "height": 44}, "region_attributes": {}}, {"shape_attributes": {"name": "rect", "x": 758, "y": 436, "width": 49, "height": 44}, "region_attributes": {}}, {"shape_attributes": {"name": "rect", "x": 881, "y": 622, "width": 57, "height": 56}, "region_attributes": {}}], "file_attributes": {}}}