{"124.jpg99771": {"filename": "124.jpg", "size": 99771, "regions": [{"shape_attributes": {"name": "rect", "x": 1407, "y": 866, "width": 36, "height": 48}, "region_attributes": {}}, {"shape_attributes": {"name": "rect", "x": 1302, "y": 924, "width": 34, "height": 43}, "region_attributes": {}}, {"shape_attributes": {"name": "rect", "x": 797, "y": 734, "width": 27, "height": 36}, "region_attributes": {}}, {"shape_attributes": {"name": "rect", "x": 1473, "y": 848, "width": 33, "height": 43}, "region_attributes": {}}, {"shape_attributes": {"name": "rect", "x": 1217, "y": 851, "width": 32, "height": 45}, "region_attributes": {}}, {"shape_attributes": {"name": "rect", "x": 1557, "y": 617, "width": 21, "height": 24}, "region_attributes": {}}, {"shape_attributes": {"name": "rect", "x": 1183, "y": 547, "width": 18, "height": 28}, "region_attributes": {}}, {"shape_attributes": {"name": "rect", "x": 184, "y": 559, "width": 22, "height": 24}, "region_attributes": {}}, {"shape_attributes": {"name": "rect", "x": 65, "y": 601, "width": 23, "height": 23}, "region_attributes": {}}, {"shape_attributes": {"name": "rect", "x": 366, "y": 613, "width": 20, "height": 24}, "region_attributes": {}}, {"shape_attributes": {"name": "rect", "x": 315, "y": 583, "width": 21, "height": 28}, "region_attributes": {}}, {"shape_attributes": {"name": "rect", "x": 550, "y": 616, "width": 20, "height": 26}, "region_attributes": {}}, {"shape_attributes": {"name": "rect", "x": 1618, "y": 658, "width": 26, "height": 29}, "region_attributes": {}}, {"shape_attributes": {"name": "rect", "x": 1594, "y": 810, "width": 30, "height": 42}, "region_attributes": {}}, {"shape_attributes": {"name": "rect", "x": 245, "y": 641, "width": 19, "height": 25}, "region_attributes": {}}, {"shape_attributes": {"name": "rect", "x": 1013, "y": 537, "width": 18, "height": 22}, "region_attributes": {}}, {"shape_attributes": {"name": "rect", "x": 1219, "y": 705, "width": 25, "height": 31}, "region_attributes": {}}, {"shape_attributes": {"name": "rect", "x": 520, "y": 670, "width": 24, "height": 28}, "region_attributes": {}}, {"shape_attributes": {"name": "rect", "x": 1708, "y": 807, "width": 31, "height": 37}, "region_attributes": {}}, {"shape_attributes": {"name": "rect", "x": 292, "y": 700, "width": 24, "height": 32}, "region_attributes": {}}, {"shape_attributes": {"name": "rect", "x": 178, "y": 641, "width": 21, "height": 27}, "region_attributes": {}}, {"shape_attributes": {"name": "rect", "x": 22, "y": 617, "width": 25, "height": 24}, "region_attributes": {}}, {"shape_attributes": {"name": "rect", "x": 499, "y": 699, "width": 28, "height": 32}, "region_attributes": {}}, {"shape_attributes": {"name": "rect", "x": 318, "y": 688, "width": 23, "height": 29}, "region_attributes": {}}, {"shape_attributes": {"name": "rect", "x": 351, "y": 678, "width": 20, "height": 26}, "region_attributes": {}}, {"shape_attributes": {"name": "rect", "x": 1237, "y": 529, "width": 13, "height": 15}, "region_attributes": {}}, {"shape_attributes": {"name": "rect", "x": 137, "y": 562, "width": 21, "height": 25}, "region_attributes": {}}, {"shape_attributes": {"name": "rect", "x": 1709, "y": 952, "width": 43, "height": 44}, "region_attributes": {}}, {"shape_attributes": {"name": "rect", "x": 380, "y": 666, "width": 21, "height": 26}, "region_attributes": {}}, {"shape_attributes": {"name": "rect", "x": 548, "y": 657, "width": 21, "height": 29}, "region_attributes": {}}, {"shape_attributes": {"name": "rect", "x": 109, "y": 607, "width": 24, "height": 24}, "region_attributes": {}}, {"shape_attributes": {"name": "rect", "x": 102, "y": 578, "width": 21, "height": 21}, "region_attributes": {}}, {"shape_attributes": {"name": "rect", "x": 126, "y": 498, "width": 28, "height": 25}, "region_attributes": {}}, {"shape_attributes": {"name": "rect", "x": 19, "y": 639, "width": 19, "height": 25}, "region_attributes": {}}], "file_attributes": {}}}