{"070.jpg79673": {"filename": "070.jpg", "size": 79673, "regions": [{"shape_attributes": {"name": "rect", "x": 62, "y": 165, "width": 44, "height": 54}, "region_attributes": {}}, {"shape_attributes": {"name": "rect", "x": 133, "y": 278, "width": 37, "height": 47}, "region_attributes": {}}, {"shape_attributes": {"name": "rect", "x": 135, "y": 364, "width": 40, "height": 34}, "region_attributes": {}}, {"shape_attributes": {"name": "rect", "x": 267, "y": 282, "width": 30, "height": 40}, "region_attributes": {}}, {"shape_attributes": {"name": "rect", "x": 268, "y": 208, "width": 29, "height": 44}, "region_attributes": {}}, {"shape_attributes": {"name": "rect", "x": 326, "y": 29, "width": 34, "height": 34}, "region_attributes": {}}, {"shape_attributes": {"name": "rect", "x": 504, "y": 159, "width": 34, "height": 37}, "region_attributes": {}}, {"shape_attributes": {"name": "rect", "x": 596, "y": 89, "width": 25, "height": 32}, "region_attributes": {}}, {"shape_attributes": {"name": "rect", "x": 678, "y": 130, "width": 30, "height": 39}, "region_attributes": {}}, {"shape_attributes": {"name": "rect", "x": 474, "y": 253, "width": 44, "height": 56}, "region_attributes": {}}, {"shape_attributes": {"name": "rect", "x": 648, "y": 528, "width": 40, "height": 51}, "region_attributes": {}}, {"shape_attributes": {"name": "rect", "x": 682, "y": 552, "width": 46, "height": 59}, "region_attributes": {}}, {"shape_attributes": {"name": "rect", "x": 815, "y": 677, "width": 52, "height": 62}, "region_attributes": {}}, {"shape_attributes": {"name": "rect", "x": 768, "y": 936, "width": 44, "height": 61}, "region_attributes": {}}, {"shape_attributes": {"name": "rect", "x": 724, "y": 791, "width": 42, "height": 59}, "region_attributes": {}}, {"shape_attributes": {"name": "rect", "x": 474, "y": 871, "width": 76, "height": 64}, "region_attributes": {}}, {"shape_attributes": {"name": "rect", "x": 427, "y": 817, "width": 52, "height": 67}, "region_attributes": {}}, {"shape_attributes": {"name": "rect", "x": 267, "y": 709, "width": 51, "height": 51}, "region_attributes": {}}, {"shape_attributes": {"name": "rect", "x": 128, "y": 898, "width": 56, "height": 67}, "region_attributes": {}}, {"shape_attributes": {"name": "rect", "x": 321, "y": 499, "width": 37, "height": 40}, "region_attributes": {}}, {"shape_attributes": {"name": "rect", "x": 337, "y": 464, "width": 47, "height": 51}, "region_attributes": {}}], "file_attributes": {}}}