{"129.jpg73094": {"filename": "129.jpg", "size": 73094, "regions": [{"shape_attributes": {"name": "rect", "x": 1757, "y": 638, "width": 79, "height": 79}, "region_attributes": {}}, {"shape_attributes": {"name": "rect", "x": 655, "y": 565, "width": 40, "height": 41}, "region_attributes": {}}, {"shape_attributes": {"name": "rect", "x": 1803, "y": 519, "width": 35, "height": 40}, "region_attributes": {}}, {"shape_attributes": {"name": "rect", "x": 1103, "y": 434, "width": 33, "height": 41}, "region_attributes": {}}, {"shape_attributes": {"name": "rect", "x": 1632, "y": 661, "width": 60, "height": 65}, "region_attributes": {}}, {"shape_attributes": {"name": "rect", "x": 836, "y": 837, "width": 66, "height": 77}, "region_attributes": {}}, {"shape_attributes": {"name": "rect", "x": 760, "y": 595, "width": 33, "height": 45}, "region_attributes": {}}, {"shape_attributes": {"name": "rect", "x": 565, "y": 316, "width": 27, "height": 31}, "region_attributes": {}}, {"shape_attributes": {"name": "rect", "x": 1012, "y": 523, "width": 31, "height": 39}, "region_attributes": {}}, {"shape_attributes": {"name": "rect", "x": 846, "y": 707, "width": 41, "height": 46}, "region_attributes": {}}, {"shape_attributes": {"name": "rect", "x": 1064, "y": 547, "width": 26, "height": 33}, "region_attributes": {}}, {"shape_attributes": {"name": "rect", "x": 499, "y": 435, "width": 34, "height": 35}, "region_attributes": {}}, {"shape_attributes": {"name": "rect", "x": 226, "y": 257, "width": 29, "height": 29}, "region_attributes": {}}, {"shape_attributes": {"name": "rect", "x": 1623, "y": 898, "width": 122, "height": 128}, "region_attributes": {}}, {"shape_attributes": {"name": "rect", "x": 463, "y": 467, "width": 35, "height": 35}, "region_attributes": {}}, {"shape_attributes": {"name": "rect", "x": 929, "y": 427, "width": 25, "height": 34}, "region_attributes": {}}, {"shape_attributes": {"name": "rect", "x": 16, "y": 191, "width": 26, "height": 37}, "region_attributes": {}}, {"shape_attributes": {"name": "rect", "x": 541, "y": 267, "width": 21, "height": 26}, "region_attributes": {}}, {"shape_attributes": {"name": "rect", "x": 219, "y": 343, "width": 28, "height": 33}, "region_attributes": {}}, {"shape_attributes": {"name": "rect", "x": 255, "y": 312, "width": 31, "height": 37}, "region_attributes": {}}, {"shape_attributes": {"name": "rect", "x": 62, "y": 188, "width": 29, "height": 35}, "region_attributes": {}}, {"shape_attributes": {"name": "rect", "x": 746, "y": 884, "width": 61, "height": 76}, "region_attributes": {}}, {"shape_attributes": {"name": "rect", "x": 42, "y": 354, "width": 37, "height": 32}, "region_attributes": {}}, {"shape_attributes": {"name": "rect", "x": 8, "y": 322, "width": 39, "height": 40}, "region_attributes": {}}, {"shape_attributes": {"name": "rect", "x": 283, "y": 253, "width": 30, "height": 34}, "region_attributes": {}}, {"shape_attributes": {"name": "rect", "x": 364, "y": 353, "width": 40, "height": 39}, "region_attributes": {}}, {"shape_attributes": {"name": "rect", "x": 391, "y": 344, "width": 29, "height": 40}, "region_attributes": {}}, {"shape_attributes": {"name": "rect", "x": 850, "y": 504, "width": 29, "height": 42}, "region_attributes": {}}, {"shape_attributes": {"name": "rect", "x": 837, "y": 545, "width": 39, "height": 35}, "region_attributes": {}}, {"shape_attributes": {"name": "rect", "x": 1458, "y": 661, "width": 83, "height": 74}, "region_attributes": {}}, {"shape_attributes": {"name": "rect", "x": 1559, "y": 727, "width": 42, "height": 56}, "region_attributes": {}}, {"shape_attributes": {"name": "rect", "x": 1604, "y": 704, "width": 46, "height": 49}, "region_attributes": {}}], "file_attributes": {}}}