{"127.jpg63912": {"filename": "127.jpg", "size": 63912, "regions": [{"shape_attributes": {"name": "rect", "x": 493, "y": 564, "width": 69, "height": 82}, "region_attributes": {}}, {"shape_attributes": {"name": "rect", "x": 1842, "y": 417, "width": 56, "height": 67}, "region_attributes": {}}, {"shape_attributes": {"name": "rect", "x": 36, "y": 499, "width": 75, "height": 80}, "region_attributes": {}}, {"shape_attributes": {"name": "rect", "x": 1368, "y": 61, "width": 24, "height": 26}, "region_attributes": {}}, {"shape_attributes": {"name": "rect", "x": 442, "y": 149, "width": 26, "height": 30}, "region_attributes": {}}, {"shape_attributes": {"name": "rect", "x": 1771, "y": 131, "width": 26, "height": 27}, "region_attributes": {}}, {"shape_attributes": {"name": "rect", "x": 1860, "y": 185, "width": 33, "height": 38}, "region_attributes": {}}, {"shape_attributes": {"name": "rect", "x": 1289, "y": 237, "width": 35, "height": 44}, "region_attributes": {}}, {"shape_attributes": {"name": "rect", "x": 1689, "y": 101, "width": 21, "height": 26}, "region_attributes": {}}, {"shape_attributes": {"name": "rect", "x": 201, "y": 261, "width": 41, "height": 42}, "region_attributes": {}}, {"shape_attributes": {"name": "rect", "x": 1739, "y": 69, "width": 21, "height": 21}, "region_attributes": {}}, {"shape_attributes": {"name": "rect", "x": 1501, "y": 99, "width": 21, "height": 23}, "region_attributes": {}}, {"shape_attributes": {"name": "rect", "x": 1358, "y": 418, "width": 58, "height": 61}, "region_attributes": {}}, {"shape_attributes": {"name": "rect", "x": 1243, "y": 714, "width": 80, "height": 90}, "region_attributes": {}}, {"shape_attributes": {"name": "rect", "x": 604, "y": 205, "width": 29, "height": 33}, "region_attributes": {}}, {"shape_attributes": {"name": "rect", "x": 1656, "y": 447, "width": 56, "height": 69}, "region_attributes": {}}, {"shape_attributes": {"name": "rect", "x": 1620, "y": 119, "width": 20, "height": 25}, "region_attributes": {}}, {"shape_attributes": {"name": "rect", "x": 1570, "y": 207, "width": 35, "height": 44}, "region_attributes": {}}, {"shape_attributes": {"name": "rect", "x": 1544, "y": 431, "width": 53, "height": 62}, "region_attributes": {}}, {"shape_attributes": {"name": "rect", "x": 1447, "y": 177, "width": 23, "height": 30}, "region_attributes": {}}, {"shape_attributes": {"name": "rect", "x": 1470, "y": 149, "width": 28, "height": 31}, "region_attributes": {}}, {"shape_attributes": {"name": "rect", "x": 415, "y": 238, "width": 41, "height": 40}, "region_attributes": {}}, {"shape_attributes": {"name": "rect", "x": 952, "y": 165, "width": 30, "height": 32}, "region_attributes": {}}, {"shape_attributes": {"name": "rect", "x": 1709, "y": 60, "width": 19, "height": 21}, "region_attributes": {}}, {"shape_attributes": {"name": "rect", "x": 418, "y": 405, "width": 49, "height": 60}, "region_attributes": {}}, {"shape_attributes": {"name": "rect", "x": 1127, "y": 489, "width": 61, "height": 77}, "region_attributes": {}}, {"shape_attributes": {"name": "rect", "x": 1910, "y": 60, "width": 10, "height": 23}, "region_attributes": {}}, {"shape_attributes": {"name": "rect", "x": 1637, "y": 387, "width": 35, "height": 39}, "region_attributes": {}}, {"shape_attributes": {"name": "rect", "x": 1533, "y": 199, "width": 32, "height": 34}, "region_attributes": {}}, {"shape_attributes": {"name": "rect", "x": 953, "y": 334, "width": 38, "height": 30}, "region_attributes": {}}, {"shape_attributes": {"name": "rect", "x": 692, "y": 73, "width": 22, "height": 22}, "region_attributes": {}}, {"shape_attributes": {"name": "rect", "x": 702, "y": 91, "width": 24, "height": 24}, "region_attributes": {}}, {"shape_attributes": {"name": "rect", "x": 1478, "y": 251, "width": 37, "height": 44}, "region_attributes": {}}, {"shape_attributes": {"name": "rect", "x": 1367, "y": 496, "width": 62, "height": 73}, "region_attributes": {}}, {"shape_attributes": {"name": "rect", "x": 963, "y": 363, "width": 42, "height": 42}, "region_attributes": {}}, {"shape_attributes": {"name": "rect", "x": 1249, "y": 186, "width": 30, "height": 35}, "region_attributes": {}}], "file_attributes": {}}}