{"065.jpg59687": {"filename": "065.jpg", "size": 59687, "regions": [{"shape_attributes": {"name": "rect", "x": 206, "y": 203, "width": 35, "height": 37}, "region_attributes": {}}, {"shape_attributes": {"name": "rect", "x": 1193, "y": 214, "width": 30, "height": 43}, "region_attributes": {}}, {"shape_attributes": {"name": "rect", "x": 740, "y": 800, "width": 50, "height": 56}, "region_attributes": {}}, {"shape_attributes": {"name": "rect", "x": 723, "y": 220, "width": 32, "height": 44}, "region_attributes": {}}, {"shape_attributes": {"name": "rect", "x": 498, "y": 349, "width": 38, "height": 38}, "region_attributes": {}}, {"shape_attributes": {"name": "rect", "x": 848, "y": 282, "width": 32, "height": 36}, "region_attributes": {}}, {"shape_attributes": {"name": "rect", "x": 1292, "y": 212, "width": 34, "height": 40}, "region_attributes": {}}, {"shape_attributes": {"name": "rect", "x": 671, "y": 953, "width": 49, "height": 51}, "region_attributes": {}}, {"shape_attributes": {"name": "rect", "x": 1736, "y": 278, "width": 41, "height": 46}, "region_attributes": {}}, {"shape_attributes": {"name": "rect", "x": 1242, "y": 133, "width": 29, "height": 35}, "region_attributes": {}}, {"shape_attributes": {"name": "rect", "x": 1275, "y": 886, "width": 64, "height": 71}, "region_attributes": {}}, {"shape_attributes": {"name": "rect", "x": 1404, "y": 80, "width": 26, "height": 35}, "region_attributes": {}}, {"shape_attributes": {"name": "rect", "x": 713, "y": 865, "width": 54, "height": 53}, "region_attributes": {}}, {"shape_attributes": {"name": "rect", "x": 589, "y": 212, "width": 35, "height": 45}, "region_attributes": {}}, {"shape_attributes": {"name": "rect", "x": 1758, "y": 676, "width": 48, "height": 54}, "region_attributes": {}}, {"shape_attributes": {"name": "rect", "x": 1535, "y": 89, "width": 25, "height": 32}, "region_attributes": {}}, {"shape_attributes": {"name": "rect", "x": 839, "y": 927, "width": 57, "height": 59}, "region_attributes": {}}, {"shape_attributes": {"name": "rect", "x": 1045, "y": 223, "width": 29, "height": 39}, "region_attributes": {}}, {"shape_attributes": {"name": "rect", "x": 1196, "y": 306, "width": 31, "height": 38}, "region_attributes": {}}, {"shape_attributes": {"name": "rect", "x": 370, "y": 413, "width": 43, "height": 40}, "region_attributes": {}}, {"shape_attributes": {"name": "rect", "x": 522, "y": 301, "width": 33, "height": 39}, "region_attributes": {}}, {"shape_attributes": {"name": "rect", "x": 13, "y": 24, "width": 23, "height": 31}, "region_attributes": {}}, {"shape_attributes": {"name": "rect", "x": 0, "y": 352, "width": 30, "height": 39}, "region_attributes": {}}, {"shape_attributes": {"name": "rect", "x": 1564, "y": 16, "width": 22, "height": 27}, "region_attributes": {}}, {"shape_attributes": {"name": "rect", "x": 1038, "y": 186, "width": 31, "height": 37}, "region_attributes": {}}, {"shape_attributes": {"name": "rect", "x": 530, "y": 11, "width": 25, "height": 37}, "region_attributes": {}}, {"shape_attributes": {"name": "rect", "x": 1713, "y": 1013, "width": 72, "height": 71}, "region_attributes": {}}, {"shape_attributes": {"name": "rect", "x": 444, "y": 224, "width": 35, "height": 35}, "region_attributes": {}}, {"shape_attributes": {"name": "rect", "x": 330, "y": 163, "width": 27, "height": 31}, "region_attributes": {}}, {"shape_attributes": {"name": "rect", "x": 1904, "y": 550, "width": 23, "height": 50}, "region_attributes": {}}, {"shape_attributes": {"name": "rect", "x": 1718, "y": 372, "width": 35, "height": 42}, "region_attributes": {}}, {"shape_attributes": {"name": "rect", "x": 1695, "y": 0, "width": 19, "height": 20}, "region_attributes": {}}, {"shape_attributes": {"name": "rect", "x": 353, "y": 143, "width": 32, "height": 34}, "region_attributes": {}}, {"shape_attributes": {"name": "rect", "x": 346, "y": 219, "width": 29, "height": 40}, "region_attributes": {}}, {"shape_attributes": {"name": "rect", "x": 445, "y": 256, "width": 46, "height": 46}, "region_attributes": {}}, {"shape_attributes": {"name": "rect", "x": 1274, "y": 2, "width": 29, "height": 24}, "region_attributes": {}}, {"shape_attributes": {"name": "rect", "x": 1748, "y": 364, "width": 34, "height": 42}, "region_attributes": {}}, {"shape_attributes": {"name": "rect", "x": 1540, "y": 2, "width": 25, "height": 24}, "region_attributes": {}}], "file_attributes": {}}}