{"025.jpg56489": {"filename": "025.jpg", "size": 56489, "regions": [{"shape_attributes": {"name": "rect", "x": 1200, "y": 160, "width": 30, "height": 36}, "region_attributes": {}}, {"shape_attributes": {"name": "rect", "x": 348, "y": 755, "width": 55, "height": 55}, "region_attributes": {}}, {"shape_attributes": {"name": "rect", "x": 644, "y": 639, "width": 35, "height": 48}, "region_attributes": {}}, {"shape_attributes": {"name": "rect", "x": 1416, "y": 594, "width": 44, "height": 53}, "region_attributes": {}}, {"shape_attributes": {"name": "rect", "x": 1332, "y": 139, "width": 28, "height": 37}, "region_attributes": {}}, {"shape_attributes": {"name": "rect", "x": 562, "y": 642, "width": 52, "height": 54}, "region_attributes": {}}, {"shape_attributes": {"name": "rect", "x": 714, "y": 107, "width": 27, "height": 38}, "region_attributes": {}}, {"shape_attributes": {"name": "rect", "x": 904, "y": 572, "width": 38, "height": 44}, "region_attributes": {}}, {"shape_attributes": {"name": "rect", "x": 1170, "y": 777, "width": 46, "height": 51}, "region_attributes": {}}, {"shape_attributes": {"name": "rect", "x": 536, "y": 288, "width": 38, "height": 43}, "region_attributes": {}}, {"shape_attributes": {"name": "rect", "x": 762, "y": 156, "width": 30, "height": 42}, "region_attributes": {}}, {"shape_attributes": {"name": "rect", "x": 866, "y": 630, "width": 43, "height": 46}, "region_attributes": {}}, {"shape_attributes": {"name": "rect", "x": 1291, "y": 176, "width": 29, "height": 35}, "region_attributes": {}}, {"shape_attributes": {"name": "rect", "x": 1249, "y": 305, "width": 37, "height": 45}, "region_attributes": {}}, {"shape_attributes": {"name": "rect", "x": 1547, "y": 652, "width": 47, "height": 53}, "region_attributes": {}}, {"shape_attributes": {"name": "rect", "x": 1696, "y": 861, "width": 47, "height": 62}, "region_attributes": {}}, {"shape_attributes": {"name": "rect", "x": 566, "y": 283, "width": 36, "height": 39}, "region_attributes": {}}, {"shape_attributes": {"name": "rect", "x": 1668, "y": 426, "width": 42, "height": 55}, "region_attributes": {}}, {"shape_attributes": {"name": "rect", "x": 1861, "y": 437, "width": 48, "height": 61}, "region_attributes": {}}, {"shape_attributes": {"name": "rect", "x": 1317, "y": 951, "width": 51, "height": 76}, "region_attributes": {}}, {"shape_attributes": {"name": "rect", "x": 1311, "y": 212, "width": 27, "height": 28}, "region_attributes": {}}, {"shape_attributes": {"name": "rect", "x": 1335, "y": 235, "width": 32, "height": 37}, "region_attributes": {}}, {"shape_attributes": {"name": "rect", "x": 161, "y": 4, "width": 19, "height": 13}, "region_attributes": {}}], "file_attributes": {}}}