{"025.jpg54961": {"filename": "025.jpg", "size": 54961, "regions": [{"shape_attributes": {"name": "rect", "x": 46, "y": 357, "width": 35, "height": 41}, "region_attributes": {}}, {"shape_attributes": {"name": "rect", "x": 895, "y": 493, "width": 36, "height": 51}, "region_attributes": {}}, {"shape_attributes": {"name": "rect", "x": 1531, "y": 95, "width": 31, "height": 37}, "region_attributes": {}}, {"shape_attributes": {"name": "rect", "x": 868, "y": 906, "width": 45, "height": 55}, "region_attributes": {}}, {"shape_attributes": {"name": "rect", "x": 1006, "y": 467, "width": 38, "height": 54}, "region_attributes": {}}, {"shape_attributes": {"name": "rect", "x": 1421, "y": 945, "width": 44, "height": 63}, "region_attributes": {}}, {"shape_attributes": {"name": "rect", "x": 509, "y": 409, "width": 37, "height": 47}, "region_attributes": {}}, {"shape_attributes": {"name": "rect", "x": 615, "y": 208, "width": 35, "height": 35}, "region_attributes": {}}, {"shape_attributes": {"name": "rect", "x": 1713, "y": 171, "width": 37, "height": 40}, "region_attributes": {}}, {"shape_attributes": {"name": "rect", "x": 1051, "y": 50, "width": 25, "height": 34}, "region_attributes": {}}, {"shape_attributes": {"name": "rect", "x": 340, "y": 242, "width": 28, "height": 37}, "region_attributes": {}}, {"shape_attributes": {"name": "rect", "x": 1756, "y": 161, "width": 38, "height": 40}, "region_attributes": {}}, {"shape_attributes": {"name": "rect", "x": 1129, "y": 34, "width": 24, "height": 36}, "region_attributes": {}}, {"shape_attributes": {"name": "rect", "x": 1142, "y": 63, "width": 28, "height": 36}, "region_attributes": {}}, {"shape_attributes": {"name": "rect", "x": 1792, "y": 194, "width": 34, "height": 40}, "region_attributes": {}}, {"shape_attributes": {"name": "rect", "x": 128, "y": 466, "width": 38, "height": 48}, "region_attributes": {}}, {"shape_attributes": {"name": "rect", "x": 746, "y": 307, "width": 38, "height": 52}, "region_attributes": {}}, {"shape_attributes": {"name": "rect", "x": 682, "y": 225, "width": 28, "height": 34}, "region_attributes": {}}, {"shape_attributes": {"name": "rect", "x": 249, "y": 300, "width": 31, "height": 39}, "region_attributes": {}}, {"shape_attributes": {"name": "rect", "x": 1603, "y": 596, "width": 42, "height": 54}, "region_attributes": {}}, {"shape_attributes": {"name": "rect", "x": 1449, "y": 859, "width": 44, "height": 63}, "region_attributes": {}}, {"shape_attributes": {"name": "rect", "x": 1566, "y": 1004, "width": 49, "height": 62}, "region_attributes": {}}, {"shape_attributes": {"name": "rect", "x": 1301, "y": 876, "width": 60, "height": 65}, "region_attributes": {}}, {"shape_attributes": {"name": "rect", "x": 256, "y": 274, "width": 35, "height": 35}, "region_attributes": {}}, {"shape_attributes": {"name": "rect", "x": 34, "y": 681, "width": 46, "height": 45}, "region_attributes": {}}, {"shape_attributes": {"name": "rect", "x": 5, "y": 722, "width": 30, "height": 49}, "region_attributes": {}}], "file_attributes": {}}}