{"140.jpg93305": {"filename": "140.jpg", "size": 93305, "regions": [{"shape_attributes": {"name": "rect", "x": 633, "y": 192, "width": 30, "height": 33}, "region_attributes": {}}, {"shape_attributes": {"name": "rect", "x": 421, "y": 312, "width": 34, "height": 40}, "region_attributes": {}}, {"shape_attributes": {"name": "rect", "x": 885, "y": 590, "width": 31, "height": 44}, "region_attributes": {}}, {"shape_attributes": {"name": "rect", "x": 706, "y": 100, "width": 30, "height": 34}, "region_attributes": {}}, {"shape_attributes": {"name": "rect", "x": 327, "y": 339, "width": 35, "height": 33}, "region_attributes": {}}, {"shape_attributes": {"name": "rect", "x": 696, "y": 213, "width": 35, "height": 33}, "region_attributes": {}}, {"shape_attributes": {"name": "rect", "x": 180, "y": 294, "width": 31, "height": 29}, "region_attributes": {}}, {"shape_attributes": {"name": "rect", "x": 950, "y": 351, "width": 32, "height": 39}, "region_attributes": {}}, {"shape_attributes": {"name": "rect", "x": 378, "y": 383, "width": 33, "height": 31}, "region_attributes": {}}, {"shape_attributes": {"name": "rect", "x": 252, "y": 469, "width": 34, "height": 33}, "region_attributes": {}}, {"shape_attributes": {"name": "rect", "x": 1410, "y": 481, "width": 40, "height": 38}, "region_attributes": {}}, {"shape_attributes": {"name": "rect", "x": 1721, "y": 1017, "width": 42, "height": 44}, "region_attributes": {}}, {"shape_attributes": {"name": "rect", "x": 206, "y": 521, "width": 36, "height": 30}, "region_attributes": {}}, {"shape_attributes": {"name": "rect", "x": 93, "y": 857, "width": 34, "height": 41}, "region_attributes": {}}, {"shape_attributes": {"name": "rect", "x": 405, "y": 577, "width": 41, "height": 31}, "region_attributes": {}}, {"shape_attributes": {"name": "rect", "x": 690, "y": 671, "width": 40, "height": 29}, "region_attributes": {}}, {"shape_attributes": {"name": "rect", "x": 821, "y": 744, "width": 33, "height": 29}, "region_attributes": {}}, {"shape_attributes": {"name": "rect", "x": 834, "y": 784, "width": 37, "height": 39}, "region_attributes": {}}, {"shape_attributes": {"name": "rect", "x": 735, "y": 1020, "width": 33, "height": 36}, "region_attributes": {}}, {"shape_attributes": {"name": "rect", "x": 793, "y": 966, "width": 44, "height": 41}, "region_attributes": {}}, {"shape_attributes": {"name": "rect", "x": 894, "y": 1032, "width": 39, "height": 39}, "region_attributes": {}}, {"shape_attributes": {"name": "rect", "x": 1094, "y": 743, "width": 41, "height": 41}, "region_attributes": {}}, {"shape_attributes": {"name": "rect", "x": 1701, "y": 755, "width": 41, "height": 47}, "region_attributes": {}}], "file_attributes": {}}}