{"020.jpg66665": {"filename": "020.jpg", "size": 66665, "regions": [{"shape_attributes": {"name": "rect", "x": 910, "y": 486, "width": 14, "height": 16}, "region_attributes": {}}, {"shape_attributes": {"name": "rect", "x": 729, "y": 615, "width": 23, "height": 31}, "region_attributes": {}}, {"shape_attributes": {"name": "rect", "x": 818, "y": 590, "width": 21, "height": 27}, "region_attributes": {}}, {"shape_attributes": {"name": "rect", "x": 871, "y": 579, "width": 20, "height": 27}, "region_attributes": {}}, {"shape_attributes": {"name": "rect", "x": 946, "y": 489, "width": 14, "height": 16}, "region_attributes": {}}, {"shape_attributes": {"name": "rect", "x": 993, "y": 528, "width": 17, "height": 23}, "region_attributes": {}}, {"shape_attributes": {"name": "rect", "x": 1250, "y": 500, "width": 19, "height": 24}, "region_attributes": {}}, {"shape_attributes": {"name": "rect", "x": 984, "y": 556, "width": 25, "height": 29}, "region_attributes": {}}, {"shape_attributes": {"name": "rect", "x": 1079, "y": 509, "width": 14, "height": 20}, "region_attributes": {}}, {"shape_attributes": {"name": "rect", "x": 963, "y": 459, "width": 12, "height": 16}, "region_attributes": {}}, {"shape_attributes": {"name": "rect", "x": 1147, "y": 468, "width": 18, "height": 20}, "region_attributes": {}}], "file_attributes": {}}}