{"139.jpg69668": {"filename": "139.jpg", "size": 69668, "regions": [{"shape_attributes": {"name": "rect", "x": 740, "y": 831, "width": 32, "height": 46}, "region_attributes": {}}, {"shape_attributes": {"name": "rect", "x": 859, "y": 790, "width": 26, "height": 45}, "region_attributes": {}}, {"shape_attributes": {"name": "rect", "x": 953, "y": 784, "width": 29, "height": 49}, "region_attributes": {}}, {"shape_attributes": {"name": "rect", "x": 1105, "y": 871, "width": 38, "height": 43}, "region_attributes": {}}, {"shape_attributes": {"name": "rect", "x": 869, "y": 469, "width": 15, "height": 17}, "region_attributes": {}}, {"shape_attributes": {"name": "rect", "x": 983, "y": 556, "width": 17, "height": 22}, "region_attributes": {}}, {"shape_attributes": {"name": "rect", "x": 945, "y": 461, "width": 11, "height": 15}, "region_attributes": {}}, {"shape_attributes": {"name": "rect", "x": 1250, "y": 509, "width": 22, "height": 29}, "region_attributes": {}}, {"shape_attributes": {"name": "rect", "x": 968, "y": 462, "width": 9, "height": 13}, "region_attributes": {}}, {"shape_attributes": {"name": "rect", "x": 1053, "y": 568, "width": 16, "height": 23}, "region_attributes": {}}, {"shape_attributes": {"name": "rect", "x": 1048, "y": 431, "width": 12, "height": 15}, "region_attributes": {}}, {"shape_attributes": {"name": "rect", "x": 1153, "y": 478, "width": 14, "height": 16}, "region_attributes": {}}, {"shape_attributes": {"name": "rect", "x": 1140, "y": 1033, "width": 34, "height": 34}, "region_attributes": {}}, {"shape_attributes": {"name": "rect", "x": 1802, "y": 477, "width": 24, "height": 25}, "region_attributes": {}}], "file_attributes": {}}}