{"018.jpg52961": {"filename": "018.jpg", "size": 52961, "regions": [{"shape_attributes": {"name": "rect", "x": 653, "y": 355, "width": 29, "height": 40}, "region_attributes": {}}, {"shape_attributes": {"name": "rect", "x": 1245, "y": 880, "width": 48, "height": 54}, "region_attributes": {}}, {"shape_attributes": {"name": "rect", "x": 1490, "y": 583, "width": 46, "height": 53}, "region_attributes": {}}, {"shape_attributes": {"name": "rect", "x": 1478, "y": 988, "width": 52, "height": 59}, "region_attributes": {}}, {"shape_attributes": {"name": "rect", "x": 1202, "y": 71, "width": 22, "height": 35}, "region_attributes": {}}, {"shape_attributes": {"name": "rect", "x": 1439, "y": 151, "width": 25, "height": 34}, "region_attributes": {}}, {"shape_attributes": {"name": "rect", "x": 1349, "y": 130, "width": 24, "height": 29}, "region_attributes": {}}, {"shape_attributes": {"name": "rect", "x": 1154, "y": 73, "width": 21, "height": 30}, "region_attributes": {}}, {"shape_attributes": {"name": "rect", "x": 1222, "y": 116, "width": 27, "height": 37}, "region_attributes": {}}, {"shape_attributes": {"name": "rect", "x": 1480, "y": 112, "width": 25, "height": 35}, "region_attributes": {}}, {"shape_attributes": {"name": "rect", "x": 41, "y": 239, "width": 37, "height": 38}, "region_attributes": {}}, {"shape_attributes": {"name": "rect", "x": 1445, "y": 612, "width": 48, "height": 53}, "region_attributes": {}}, {"shape_attributes": {"name": "rect", "x": 452, "y": 19, "width": 20, "height": 30}, "region_attributes": {}}, {"shape_attributes": {"name": "rect", "x": 314, "y": 50, "width": 28, "height": 30}, "region_attributes": {}}, {"shape_attributes": {"name": "rect", "x": 1286, "y": 77, "width": 24, "height": 29}, "region_attributes": {}}, {"shape_attributes": {"name": "rect", "x": 1637, "y": 166, "width": 30, "height": 35}, "region_attributes": {}}, {"shape_attributes": {"name": "rect", "x": 1260, "y": 148, "width": 25, "height": 31}, "region_attributes": {}}, {"shape_attributes": {"name": "rect", "x": 1542, "y": 144, "width": 24, "height": 24}, "region_attributes": {}}, {"shape_attributes": {"name": "rect", "x": 340, "y": 72, "width": 15, "height": 21}, "region_attributes": {}}], "file_attributes": {}}}